cyclic/__init__.py
cyclic/cyclic.py
cyclic/version.py
cyclic-1.0.0.dist-info/METADATA
cyclic-1.0.0.dist-info/RECORD
cyclic-1.0.0.dist-info/WHEEL
cyclic-1.0.0.dist-info/top_level.txt
