Metadata-Version: 2.1
Name: cyclic
Version: 1.0.0
Summary: Handle cyclic relations
Home-page: https://github.com/neurobin/cyclic
Author: Md. Jahidul Hamid
Author-email: jahidulhamid@yahoo.com
License: BSD
Keywords: cyclic relation circular dependency
Platform: UNKNOWN
Classifier: Development Status :: 5 - Production/Stable
Classifier: Intended Audience :: Developers
Classifier: Intended Audience :: Information Technology
Classifier: License :: OSI Approved :: BSD License
Classifier: Operating System :: OS Independent
Classifier: Programming Language :: Python
Classifier: Programming Language :: Python :: 2
Classifier: Programming Language :: Python :: 3
